gch747/__init__.py
gch747/fct_PCA_NIPALS.py
gch747/fct_PCA_SVD.py
gch747/fct_flip.py
gch747/fct_normplot.py
gch747/fct_regress.py
gch747/fct_xlsread.py
gch747-0.0.5.dist-info/METADATA
gch747-0.0.5.dist-info/WHEEL
gch747-0.0.5.dist-info/top_level.txt
gch747-0.0.5.dist-info/RECORD
