Metadata-Version: 2.1
Name: gch747
Version: 0.0.5
Summary: misc stuff
Home-page: UNKNOWN
Author: Ryan Gosselin
Author-email: ryan.gosselin@usherbrooke.ca
License: UNKNOWN
Platform: UNKNOWN
Classifier: Programming Language :: Python :: 3
Classifier: License :: OSI Approved :: MIT License
Classifier: Operating System :: OS Independent
